sitecustomize.py
yprint/__init__.py
yprint/__main__.py
yprint/auto.py
yprint/cli.py
yprint/prefix.py
yprint/terminal.py
yprint/yprint_preload.c
yprint-0.1.1.dist-info/METADATA
yprint-0.1.1.dist-info/WHEEL
yprint-0.1.1.dist-info/entry_points.txt
yprint-0.1.1.dist-info/top_level.txt
yprint-0.1.1.dist-info/RECORD
