Metadata-Version: 2.4
Name: yprint
Version: 0.1.1
Summary: Prefix stdout/stderr lines with call stack context.
Requires-Python: >=3.8
Provides-Extra: dev
Requires-Dist: build>=1.0; extra == "dev"
Requires-Dist: twine>=4.0; extra == "dev"
